{
  "id": "0e6f8680-3d30-4525-913c-d1a122106452",
  "prevId": "31878da9-b945-4db4-afe8-6c35a4e7525a",
  "version": "7",
  "dialect": "postgresql",
  "tables": {
    "public.activities": {
      "name": "activities",
      "schema": "",
      "columns": {
        "id": {
          "name": "id",
          "type": "serial",
          "primaryKey": true,
          "notNull": true
        },
        "title": {
          "name": "title",
          "type": "varchar(255)",
          "primaryKey": false,
          "notNull": true
        },
        "activity_type": {
          "name": "activity_type",
          "type": "varchar(100)",
          "primaryKey": false,
          "notNull": true
        },
        "start_time": {
          "name": "start_time",
          "type": "timestamp with time zone",
          "primaryKey": false,
          "notNull": true
        },
        "end_time": {
          "name": "end_time",
          "type": "timestamp with time zone",
          "primaryKey": false,
          "notNull": false
        },
        "location": {
          "name": "location",
          "type": "varchar(255)",
          "primaryKey": false,
          "notNull": false
        },
        "capacity": {
          "name": "capacity",
          "type": "integer",
          "primaryKey": false,
          "notNull": false
        },
        "participant_count": {
          "name": "participant_count",
          "type": "integer",
          "primaryKey": false,
          "notNull": true,
          "default": 0
        },
        "requires_golfbox_reservation": {
          "name": "requires_golfbox_reservation",
          "type": "boolean",
          "primaryKey": false,
          "notNull": true,
          "default": false
        },
        "golfbox_reservation_completed": {
          "name": "golfbox_reservation_completed",
          "type": "boolean",
          "primaryKey": false,
          "notNull": true,
          "default": false
        },
        "golfbox_reservation_note": {
          "name": "golfbox_reservation_note",
          "type": "text",
          "primaryKey": false,
          "notNull": false
        },
        "created_at": {
          "name": "created_at",
          "type": "timestamp with time zone",
          "primaryKey": false,
          "notNull": true,
          "default": "now()"
        },
        "updated_at": {
          "name": "updated_at",
          "type": "timestamp with time zone",
          "primaryKey": false,
          "notNull": true,
          "default": "now()"
        }
      },
      "indexes": {},
      "foreignKeys": {},
      "compositePrimaryKeys": {},
      "uniqueConstraints": {},
      "policies": {},
      "checkConstraints": {},
      "isRLSEnabled": false
    },
    "public.activity_trainers": {
      "name": "activity_trainers",
      "schema": "",
      "columns": {
        "activity_id": {
          "name": "activity_id",
          "type": "integer",
          "primaryKey": false,
          "notNull": true
        },
        "trainer_id": {
          "name": "trainer_id",
          "type": "integer",
          "primaryKey": false,
          "notNull": true
        }
      },
      "indexes": {},
      "foreignKeys": {
        "activity_trainers_activity_id_activities_id_fk": {
          "name": "activity_trainers_activity_id_activities_id_fk",
          "tableFrom": "activity_trainers",
          "tableTo": "activities",
          "columnsFrom": [
            "activity_id"
          ],
          "columnsTo": [
            "id"
          ],
          "onDelete": "cascade",
          "onUpdate": "no action"
        },
        "activity_trainers_trainer_id_trainers_id_fk": {
          "name": "activity_trainers_trainer_id_trainers_id_fk",
          "tableFrom": "activity_trainers",
          "tableTo": "trainers",
          "columnsFrom": [
            "trainer_id"
          ],
          "columnsTo": [
            "id"
          ],
          "onDelete": "cascade",
          "onUpdate": "no action"
        }
      },
      "compositePrimaryKeys": {
        "activity_trainers_activity_id_trainer_id_pk": {
          "name": "activity_trainers_activity_id_trainer_id_pk",
          "columns": [
            "activity_id",
            "trainer_id"
          ]
        }
      },
      "uniqueConstraints": {},
      "policies": {},
      "checkConstraints": {},
      "isRLSEnabled": false
    },
    "public.email_drafts": {
      "name": "email_drafts",
      "schema": "",
      "columns": {
        "id": {
          "name": "id",
          "type": "serial",
          "primaryKey": true,
          "notNull": true
        },
        "subject": {
          "name": "subject",
          "type": "varchar(255)",
          "primaryKey": false,
          "notNull": true
        },
        "to_address": {
          "name": "to_address",
          "type": "varchar(255)",
          "primaryKey": false,
          "notNull": true
        },
        "body": {
          "name": "body",
          "type": "text",
          "primaryKey": false,
          "notNull": true
        },
        "status": {
          "name": "status",
          "type": "varchar(20)",
          "primaryKey": false,
          "notNull": true,
          "default": "'pending'"
        },
        "source_thread_id": {
          "name": "source_thread_id",
          "type": "varchar(255)",
          "primaryKey": false,
          "notNull": false
        },
        "created_at": {
          "name": "created_at",
          "type": "timestamp with time zone",
          "primaryKey": false,
          "notNull": true,
          "default": "now()"
        },
        "updated_at": {
          "name": "updated_at",
          "type": "timestamp with time zone",
          "primaryKey": false,
          "notNull": true,
          "default": "now()"
        }
      },
      "indexes": {},
      "foreignKeys": {},
      "compositePrimaryKeys": {},
      "uniqueConstraints": {},
      "policies": {},
      "checkConstraints": {},
      "isRLSEnabled": false
    },
    "public.knowledge_documents": {
      "name": "knowledge_documents",
      "schema": "",
      "columns": {
        "id": {
          "name": "id",
          "type": "serial",
          "primaryKey": true,
          "notNull": true
        },
        "title": {
          "name": "title",
          "type": "varchar(255)",
          "primaryKey": false,
          "notNull": true
        },
        "category": {
          "name": "category",
          "type": "varchar(100)",
          "primaryKey": false,
          "notNull": true
        },
        "content": {
          "name": "content",
          "type": "text",
          "primaryKey": false,
          "notNull": true
        },
        "created_at": {
          "name": "created_at",
          "type": "timestamp with time zone",
          "primaryKey": false,
          "notNull": true,
          "default": "now()"
        },
        "updated_at": {
          "name": "updated_at",
          "type": "timestamp with time zone",
          "primaryKey": false,
          "notNull": true,
          "default": "now()"
        }
      },
      "indexes": {},
      "foreignKeys": {},
      "compositePrimaryKeys": {},
      "uniqueConstraints": {},
      "policies": {},
      "checkConstraints": {},
      "isRLSEnabled": false
    },
    "public.oauth_tokens": {
      "name": "oauth_tokens",
      "schema": "",
      "columns": {
        "id": {
          "name": "id",
          "type": "serial",
          "primaryKey": true,
          "notNull": true
        },
        "provider": {
          "name": "provider",
          "type": "varchar(50)",
          "primaryKey": false,
          "notNull": true
        },
        "access_token": {
          "name": "access_token",
          "type": "text",
          "primaryKey": false,
          "notNull": true
        },
        "refresh_token": {
          "name": "refresh_token",
          "type": "text",
          "primaryKey": false,
          "notNull": true
        },
        "expires_at": {
          "name": "expires_at",
          "type": "timestamp with time zone",
          "primaryKey": false,
          "notNull": true
        },
        "created_at": {
          "name": "created_at",
          "type": "timestamp with time zone",
          "primaryKey": false,
          "notNull": true,
          "default": "now()"
        }
      },
      "indexes": {},
      "foreignKeys": {},
      "compositePrimaryKeys": {},
      "uniqueConstraints": {
        "oauth_tokens_provider_unique": {
          "name": "oauth_tokens_provider_unique",
          "nullsNotDistinct": false,
          "columns": [
            "provider"
          ]
        }
      },
      "policies": {},
      "checkConstraints": {},
      "isRLSEnabled": false
    },
    "public.trainers": {
      "name": "trainers",
      "schema": "",
      "columns": {
        "id": {
          "name": "id",
          "type": "serial",
          "primaryKey": true,
          "notNull": true
        },
        "name": {
          "name": "name",
          "type": "varchar(255)",
          "primaryKey": false,
          "notNull": true
        },
        "email": {
          "name": "email",
          "type": "varchar(255)",
          "primaryKey": false,
          "notNull": false
        },
        "active": {
          "name": "active",
          "type": "boolean",
          "primaryKey": false,
          "notNull": true,
          "default": true
        },
        "created_at": {
          "name": "created_at",
          "type": "timestamp with time zone",
          "primaryKey": false,
          "notNull": true,
          "default": "now()"
        }
      },
      "indexes": {},
      "foreignKeys": {},
      "compositePrimaryKeys": {},
      "uniqueConstraints": {},
      "policies": {},
      "checkConstraints": {},
      "isRLSEnabled": false
    }
  },
  "enums": {},
  "schemas": {},
  "sequences": {},
  "roles": {},
  "policies": {},
  "views": {},
  "_meta": {
    "columns": {},
    "schemas": {},
    "tables": {}
  }
}